omics/__init__.py
omics/biomart/__init__.py
omics/expression/ExpressionSet.py
omics/expression/__init__.py
omics/io/ExpressionSetIO.py
omics/io/__init__.py
omics/stats/__init__.py
omics/stats/fisher.py
omics-0.1.2.data/scripts/biomart.py
omics-0.1.2.dist-info/DESCRIPTION.rst
omics-0.1.2.dist-info/METADATA
omics-0.1.2.dist-info/RECORD
omics-0.1.2.dist-info/WHEEL
omics-0.1.2.dist-info/metadata.json
omics-0.1.2.dist-info/top_level.txt
